pvfalcon/LICENSE
pvfalcon/__init__.py
pvfalcon/_factory.py
pvfalcon/_falcon.py
pvfalcon/_util.py
pvfalcon/lib/common/falcon_params.pv
pvfalcon/lib/linux/x86_64/libpv_falcon.so
pvfalcon/lib/mac/arm64/libpv_falcon.dylib
pvfalcon/lib/mac/x86_64/libpv_falcon.dylib
pvfalcon/lib/raspberry-pi/cortex-a53/libpv_falcon.so
pvfalcon/lib/raspberry-pi/cortex-a53-aarch64/libpv_falcon.so
pvfalcon/lib/raspberry-pi/cortex-a72/libpv_falcon.so
pvfalcon/lib/raspberry-pi/cortex-a72-aarch64/libpv_falcon.so
pvfalcon/lib/raspberry-pi/cortex-a76/libpv_falcon.so
pvfalcon/lib/raspberry-pi/cortex-a76-aarch64/libpv_falcon.so
pvfalcon/lib/windows/amd64/libpv_falcon.dll
pvfalcon/lib/windows/amd64/pv_ypu_impl_cuda.dll
pvfalcon/lib/windows/arm64/libpv_falcon.dll
pvfalcon-2.0.0.dist-info/METADATA
pvfalcon-2.0.0.dist-info/WHEEL
pvfalcon-2.0.0.dist-info/top_level.txt
pvfalcon-2.0.0.dist-info/RECORD
