Metadata-Version: 2.1
Name: pvfalcon
Version: 2.0.0
Summary: Falcon Speaker Diarization Engine
Home-page: https://github.com/Picovoice/falcon
Author: Picovoice
Author-email: hello@picovoice.ai
Keywords: Speaker Diarization,Speaker Identification,Voice Identification
Classifier: Development Status :: 5 - Production/Stable
Classifier: Intended Audience :: Developers
Classifier: License :: OSI Approved :: Apache Software License
Classifier: Operating System :: OS Independent
Classifier: Programming Language :: Python :: 3
Classifier: Topic :: Multimedia :: Sound/Audio :: Speech
Requires-Python: >=3.9
